[
  {
    "platform" : "ANDROID",
    "searchTime" : "2019-11-23T09:19:45.655Z[UTC]",
    "searchQuery" : "blood diamond soun",
    "searchInteractionURIs" : [
      "spotify:album:2YwDj8TchnUvnxekoIcQ0X"
    ]
  },
  {
    "platform" : "ANDROID",
    "searchTime" : "2019-11-24T05:24:12.398Z[UTC]",
    "searchQuery" : "hersi",
    "searchInteractionURIs" : [
      "spotify:track:564oa00vY05d1uYnTEAAmE"
    ]
  },
  {
    "platform" : "ANDROID",
    "searchTime" : "2019-11-25T21:20:11.268Z[UTC]",
    "searchQuery" : "herside",
    "searchInteractionURIs" : [
      "spotify:track:564oa00vY05d1uYnTEAAmE",
      "spotify:playlist:0ikChES0DZvzJmjynW2gQu",
      "spotify:track:564oa00vY05d1uYnTEAAmE",
      "spotify:episode:5CGvSUjjvKey77RZldBoy1"
    ]
  },
  {
    "platform" : "ANDROID",
    "searchTime" : "2019-11-25T21:37:01.758Z[UTC]",
    "searchQuery" : "perfune",
    "searchInteractionURIs" : [
      "spotify:artist:2ueoLVCXQ948OfhVvAy3Nn"
    ]
  },
  {
    "platform" : "ANDROID",
    "searchTime" : "2019-11-26T02:18:40.836Z[UTC]",
    "searchQuery" : "nside",
    "searchInteractionURIs" : [
      "spotify:track:24G1PXBWoRgV0wDXZKwxzz",
      "spotify:track:24G1PXBWoRgV0wDXZKwxzz"
    ]
  },
  {
    "platform" : "ANDROID",
    "searchTime" : "2019-11-26T02:30:21.338Z[UTC]",
    "searchQuery" : "n",
    "searchInteractionURIs" : [
      ""
    ]
  },
  {
    "platform" : "ANDROID",
    "searchTime" : "2019-11-26T02:30:22.569Z[UTC]",
    "searchQuery" : "love 2 ",
    "searchInteractionURIs" : [
      "spotify:track:7MlAND46qL6L5npwOhbaZK"
    ]
  },
  {
    "platform" : "ANDROID",
    "searchTime" : "2019-11-26T02:34:56.165Z[UTC]",
    "searchQuery" : "her",
    "searchInteractionURIs" : [
      "spotify:track:564oa00vY05d1uYnTEAAmE",
      "spotify:search:artists:her"
    ]
  },
  {
    "platform" : "ANDROID",
    "searchTime" : "2019-11-26T02:37:59.294Z[UTC]",
    "searchQuery" : "her",
    "searchInteractionURIs" : [
    ]
  },
  {
    "platform" : "ANDROID",
    "searchTime" : "2019-11-26T04:57:15.444Z[UTC]",
    "searchQuery" : "perfune",
    "searchInteractionURIs" : [
      "spotify:artist:2ueoLVCXQ948OfhVvAy3Nn"
    ]
  },
  {
    "platform" : "ANDROID",
    "searchTime" : "2019-11-26T05:20:59.193Z[UTC]",
    "searchQuery" : "er",
    "searchInteractionURIs" : [
      ""
    ]
  },
  {
    "platform" : "ANDROID",
    "searchTime" : "2019-11-26T05:21:00.671Z[UTC]",
    "searchQuery" : "perfune",
    "searchInteractionURIs" : [
      "spotify:artist:2ueoLVCXQ948OfhVvAy3Nn"
    ]
  },
  {
    "platform" : "ANDROID",
    "searchTime" : "2019-11-26T06:40:05.905Z[UTC]",
    "searchQuery" : "perfume",
    "searchInteractionURIs" : [
      "spotify:artist:2ueoLVCXQ948OfhVvAy3Nn"
    ]
  },
  {
    "platform" : "ANDROID",
    "searchTime" : "2019-11-27T07:13:35.297Z[UTC]",
    "searchQuery" : "heartle",
    "searchInteractionURIs" : [
      "spotify:track:4EWCNWgDS8707fNSZ1oaA5"
    ]
  },
  {
    "platform" : "ANDROID",
    "searchTime" : "2019-11-27T07:31:56.855Z[UTC]",
    "searchQuery" : "herside",
    "searchInteractionURIs" : [
      "spotify:track:564oa00vY05d1uYnTEAAmE"
    ]
  },
  {
    "platform" : "ANDROID",
    "searchTime" : "2019-11-27T07:35:57.407Z[UTC]",
    "searchQuery" : "son of a bitch",
    "searchInteractionURIs" : [
      "spotify:playlist:3zrhsblERlEH0WHo1nSKf9",
      ""
    ]
  },
  {
    "platform" : "ANDROID",
    "searchTime" : "2019-11-27T07:36:21.771Z[UTC]",
    "searchQuery" : "son of ",
    "searchInteractionURIs" : [
      "spotify:track:7odHgoLFi3GQ90E9PeraI3"
    ]
  },
  {
    "platform" : "ANDROID",
    "searchTime" : "2019-11-27T11:05:16.035Z[UTC]",
    "searchQuery" : "nightt",
    "searchInteractionURIs" : [
    ]
  },
  {
    "platform" : "ANDROID",
    "searchTime" : "2019-11-27T11:06:56.933Z[UTC]",
    "searchQuery" : "nigh",
    "searchInteractionURIs" : [
      ""
    ]
  },
  {
    "platform" : "ANDROID",
    "searchTime" : "2019-11-27T11:06:59.757Z[UTC]",
    "searchQuery" : "nighht",
    "searchInteractionURIs" : [
      "spotify:track:7eqoqGkKwgOaWNNHx90uEZ"
    ]
  },
  {
    "platform" : "ANDROID",
    "searchTime" : "2019-11-27T22:24:31.438Z[UTC]",
    "searchQuery" : "how to save ",
    "searchInteractionURIs" : [
      "spotify:track:5fVZC9GiM4e8vu99W0Xf6J",
      ""
    ]
  },
  {
    "platform" : "ANDROID",
    "searchTime" : "2019-11-27T22:25:00.795Z[UTC]",
    "searchQuery" : "you",
    "searchInteractionURIs" : [
      ""
    ]
  },
  {
    "platform" : "ANDROID",
    "searchTime" : "2019-11-27T22:25:01.842Z[UTC]",
    "searchQuery" : "you foun",
    "searchInteractionURIs" : [
      ""
    ]
  },
  {
    "platform" : "ANDROID",
    "searchTime" : "2019-11-27T22:27:57.017Z[UTC]",
    "searchQuery" : "you found me ",
    "searchInteractionURIs" : [
    ]
  },
  {
    "platform" : "ANDROID",
    "searchTime" : "2019-11-27T22:48:57.073Z[UTC]",
    "searchQuery" : "tuesdays",
    "searchInteractionURIs" : [
      "spotify:track:64sn7wgJfeQKY3Jisnl59w",
      ""
    ]
  },
  {
    "platform" : "ANDROID",
    "searchTime" : "2019-11-27T23:21:24.246Z[UTC]",
    "searchQuery" : "here ",
    "searchInteractionURIs" : [
      "spotify:track:6dGnYIeXmHdcikdzNNDMm2"
    ]
  },
  {
    "platform" : "ANDROID",
    "searchTime" : "2019-11-27T23:31:01.354Z[UTC]",
    "searchQuery" : "god",
    "searchInteractionURIs" : [
      "spotify:track:5p3NP9mQblDsVJLdfNZJ3I"
    ]
  },
  {
    "platform" : "ANDROID",
    "searchTime" : "2019-11-28T03:58:09.931Z[UTC]",
    "searchQuery" : "me gus",
    "searchInteractionURIs" : [
      "spotify:track:6b37xrsNCWYIUphFBazqD6"
    ]
  },
  {
    "platform" : "ANDROID",
    "searchTime" : "2019-11-29T06:37:18.121Z[UTC]",
    "searchQuery" : "n sid3",
    "searchInteractionURIs" : [
      "spotify:track:24G1PXBWoRgV0wDXZKwxzz"
    ]
  },
  {
    "platform" : "ANDROID",
    "searchTime" : "2019-11-29T06:45:57.200Z[UTC]",
    "searchQuery" : "n sid3 ",
    "searchInteractionURIs" : [
      ""
    ]
  },
  {
    "platform" : "ANDROID",
    "searchTime" : "2019-11-29T06:46:17.880Z[UTC]",
    "searchQuery" : "anjaana anjaani",
    "searchInteractionURIs" : [
      "spotify:search:tracks:anjaana%20anjaani"
    ]
  },
  {
    "platform" : "ANDROID",
    "searchTime" : "2019-11-29T06:46:22.686Z[UTC]",
    "searchQuery" : "anjaana anjaani",
    "searchInteractionURIs" : [
      "spotify:track:1R1Ydsav3CXKHS14whfs49",
      "spotify:track:1R1Ydsav3CXKHS14whfs49"
    ]
  },
  {
    "platform" : "ANDROID",
    "searchTime" : "2019-11-29T06:47:50.791Z[UTC]",
    "searchQuery" : "anjaana anjaani",
    "searchInteractionURIs" : [
    ]
  },
  {
    "platform" : "ANDROID",
    "searchTime" : "2019-11-29T06:48:38.555Z[UTC]",
    "searchQuery" : "anjaana anjaani",
    "searchInteractionURIs" : [
    ]
  },
  {
    "platform" : "ANDROID",
    "searchTime" : "2019-11-29T06:49:30.939Z[UTC]",
    "searchQuery" : "anjaana anjaani",
    "searchInteractionURIs" : [
    ]
  },
  {
    "platform" : "ANDROID",
    "searchTime" : "2019-11-29T07:10:29.738Z[UTC]",
    "searchQuery" : "anjaana anjaani",
    "searchInteractionURIs" : [
    ]
  },
  {
    "platform" : "ANDROID",
    "searchTime" : "2019-11-29T07:12:38.408Z[UTC]",
    "searchQuery" : "anjaana anjaani",
    "searchInteractionURIs" : [
    ]
  },
  {
    "platform" : "ANDROID",
    "searchTime" : "2019-11-30T00:52:26.700Z[UTC]",
    "searchQuery" : "a boy is ",
    "searchInteractionURIs" : [
      "spotify:track:1nXZnTALNXiPlvXotqHm66"
    ]
  },
  {
    "platform" : "ANDROID",
    "searchTime" : "2019-11-30T01:12:19.887Z[UTC]",
    "searchQuery" : "joe ca",
    "searchInteractionURIs" : [
      "spotify:artist:1EAmVLT4DRdhjumC9TYX1V"
    ]
  },
  {
    "platform" : "ANDROID",
    "searchTime" : "2019-11-30T01:12:24.850Z[UTC]",
    "searchQuery" : "joe cocker",
    "searchInteractionURIs" : [
      "spotify:artist:3pFCERyEiP5xeN2EsPXhjI"
    ]
  },
  {
    "platform" : "ANDROID",
    "searchTime" : "2019-11-30T01:12:32.742Z[UTC]",
    "searchQuery" : "joe cocker have a littl",
    "searchInteractionURIs" : [
      "spotify:track:5pmpRdiDKElAakxjWiXu0B",
      "spotify:playlist:2V8jZxHbNaRhOSXKCCGeqU",
      "spotify:track:5pmpRdiDKElAakxjWiXu0B"
    ]
  },
  {
    "platform" : "ANDROID",
    "searchTime" : "2019-11-30T01:15:37.645Z[UTC]",
    "searchQuery" : "sex on fire",
    "searchInteractionURIs" : [
      "spotify:track:0ntQJM78wzOLVeCUAW7Y45",
      "spotify:track:0ntQJM78wzOLVeCUAW7Y45"
    ]
  },
  {
    "platform" : "ANDROID",
    "searchTime" : "2019-11-30T01:16:15.974Z[UTC]",
    "searchQuery" : "1973",
    "searchInteractionURIs" : [
      "spotify:track:1BV0m40U0M4t1SLIsDnwZl"
    ]
  },
  {
    "platform" : "ANDROID",
    "searchTime" : "2019-11-30T01:24:57.197Z[UTC]",
    "searchQuery" : "1973",
    "searchInteractionURIs" : [
      "spotify:track:1BV0m40U0M4t1SLIsDnwZl"
    ]
  },
  {
    "platform" : "ANDROID",
    "searchTime" : "2019-11-30T01:25:28.195Z[UTC]",
    "searchQuery" : "40 mark",
    "searchInteractionURIs" : [
      "spotify:track:3klMnAnAWXdo6MomqXeJMn",
      "spotify:track:3klMnAnAWXdo6MomqXeJMn"
    ]
  },
  {
    "platform" : "ANDROID",
    "searchTime" : "2019-11-30T01:25:58.647Z[UTC]",
    "searchQuery" : "t",
    "searchInteractionURIs" : [
      ""
    ]
  },
  {
    "platform" : "ANDROID",
    "searchTime" : "2019-11-30T01:30:39.241Z[UTC]",
    "searchQuery" : "gideon",
    "searchInteractionURIs" : [
      "spotify:track:4gNhWF7BcTzNJwcSTdZ6NI"
    ]
  },
  {
    "platform" : "ANDROID",
    "searchTime" : "2019-11-30T01:33:42.447Z[UTC]",
    "searchQuery" : "all my love",
    "searchInteractionURIs" : [
      "spotify:track:6lrh9jZ1xoMwoErgPSj2rY",
      "spotify:track:6lrh9jZ1xoMwoErgPSj2rY"
    ]
  },
  {
    "platform" : "ANDROID",
    "searchTime" : "2019-11-30T01:37:25.492Z[UTC]",
    "searchQuery" : "al",
    "searchInteractionURIs" : [
      ""
    ]
  },
  {
    "platform" : "ANDROID",
    "searchTime" : "2019-11-30T02:03:44.604Z[UTC]",
    "searchQuery" : "doves ",
    "searchInteractionURIs" : [
      "spotify:track:593W4qZOwwdqF6YnimJjL6"
    ]
  },
  {
    "platform" : "ANDROID",
    "searchTime" : "2019-11-30T02:07:02.745Z[UTC]",
    "searchQuery" : "doves p",
    "searchInteractionURIs" : [
    ]
  },
  {
    "platform" : "ANDROID",
    "searchTime" : "2019-11-30T03:11:16.661Z[UTC]",
    "searchQuery" : "this feelin",
    "searchInteractionURIs" : [
      "spotify:track:3IBhpCAFOJxynTfrw0t2LN",
      ""
    ]
  },
  {
    "platform" : "ANDROID",
    "searchTime" : "2019-11-30T03:14:08.911Z[UTC]",
    "searchQuery" : "cold ",
    "searchInteractionURIs" : [
      "spotify:album:55A6d8TOuiAs6zDiKj2c3A"
    ]
  },
  {
    "platform" : "ANDROID",
    "searchTime" : "2019-11-30T03:18:31.729Z[UTC]",
    "searchQuery" : "brown eyed women ",
    "searchInteractionURIs" : [
      "spotify:playlist:0CrtlsxT6FCxRmAQ6RhqUC",
      "spotify:track:5d7fWLYYJReMfeUqfJqns0",
      "spotify:track:1BlJdQjT6QYjRlfP0C1rz1"
    ]
  },
  {
    "platform" : "ANDROID",
    "searchTime" : "2019-11-30T03:28:48.258Z[UTC]",
    "searchQuery" : "super",
    "searchInteractionURIs" : [
      "spotify:track:0725YWm6Z0TpZ6wrNk64Eb",
      "spotify:track:67YPjbcxUypwNOwYBZquq1",
      "spotify:track:0725YWm6Z0TpZ6wrNk64Eb",
      ""
    ]
  },
  {
    "platform" : "ANDROID",
    "searchTime" : "2019-11-30T03:32:52.814Z[UTC]",
    "searchQuery" : "c",
    "searchInteractionURIs" : [
      ""
    ]
  },
  {
    "platform" : "ANDROID",
    "searchTime" : "2019-11-30T03:32:54.142Z[UTC]",
    "searchQuery" : "ch",
    "searchInteractionURIs" : [
      ""
    ]
  },
  {
    "platform" : "ANDROID",
    "searchTime" : "2019-11-30T03:32:55.481Z[UTC]",
    "searchQuery" : "channel",
    "searchInteractionURIs" : [
      "spotify:album:392p3shh2jkxUxY2VHvlH8"
    ]
  },
  {
    "platform" : "ANDROID",
    "searchTime" : "2019-11-30T03:43:49.667Z[UTC]",
    "searchQuery" : "ch",
    "searchInteractionURIs" : [
      ""
    ]
  },
  {
    "platform" : "ANDROID",
    "searchTime" : "2019-11-30T03:44:02.068Z[UTC]",
    "searchQuery" : "fr",
    "searchInteractionURIs" : [
      ""
    ]
  },
  {
    "platform" : "ANDROID",
    "searchTime" : "2019-11-30T03:44:03.339Z[UTC]",
    "searchQuery" : "blon",
    "searchInteractionURIs" : [
      "spotify:album:3mH6qwIy9crq0I9YQbOuDf"
    ]
  },
  {
    "platform" : "ANDROID",
    "searchTime" : "2019-11-30T03:51:41.899Z[UTC]",
    "searchQuery" : "damn",
    "searchInteractionURIs" : [
      "spotify:album:4eLPsYPBmXABThSJ821sqY"
    ]
  },
  {
    "platform" : "ANDROID",
    "searchTime" : "2019-11-30T03:52:07.022Z[UTC]",
    "searchQuery" : "d",
    "searchInteractionURIs" : [
      ""
    ]
  },
  {
    "platform" : "ANDROID",
    "searchTime" : "2019-11-30T03:52:09.162Z[UTC]",
    "searchQuery" : "good mid",
    "searchInteractionURIs" : [
      "spotify:album:3DGQ1iZ9XKUQxAUWjfC34w"
    ]
  },
  {
    "platform" : "ANDROID",
    "searchTime" : "2019-11-30T04:08:50.571Z[UTC]",
    "searchQuery" : "goo",
    "searchInteractionURIs" : [
      ""
    ]
  },
  {
    "platform" : "ANDROID",
    "searchTime" : "2019-11-30T04:08:52.719Z[UTC]",
    "searchQuery" : "to pimp",
    "searchInteractionURIs" : [
      "spotify:album:7ycBtnsMtyVbbwTfJwRjSP"
    ]
  },
  {
    "platform" : "ANDROID",
    "searchTime" : "2019-11-30T04:26:18.676Z[UTC]",
    "searchQuery" : "mr",
    "searchInteractionURIs" : [
      ""
    ]
  },
  {
    "platform" : "ANDROID",
    "searchTime" : "2019-11-30T04:26:20.162Z[UTC]",
    "searchQuery" : "mr ",
    "searchInteractionURIs" : [
      ""
    ]
  },
  {
    "platform" : "ANDROID",
    "searchTime" : "2019-11-30T04:26:25.698Z[UTC]",
    "searchQuery" : "bongo man",
    "searchInteractionURIs" : [
      "spotify:track:00SmB7n85SKROGjybsyq5i"
    ]
  },
  {
    "platform" : "ANDROID",
    "searchTime" : "2019-11-30T06:12:05.778Z[UTC]",
    "searchQuery" : "herside",
    "searchInteractionURIs" : [
      "spotify:track:564oa00vY05d1uYnTEAAmE",
      ""
    ]
  },
  {
    "platform" : "ANDROID",
    "searchTime" : "2019-11-30T06:14:24.652Z[UTC]",
    "searchQuery" : "hate that ",
    "searchInteractionURIs" : [
      "spotify:track:7iu0WYLdo4yksKf3seaxzI",
      ""
    ]
  },
  {
    "platform" : "ANDROID",
    "searchTime" : "2019-11-30T06:17:56.557Z[UTC]",
    "searchQuery" : "lov",
    "searchInteractionURIs" : [
      ""
    ]
  },
  {
    "platform" : "ANDROID",
    "searchTime" : "2019-11-30T06:17:56.824Z[UTC]",
    "searchQuery" : "love",
    "searchInteractionURIs" : [
      ""
    ]
  },
  {
    "platform" : "ANDROID",
    "searchTime" : "2019-11-30T06:18:00.189Z[UTC]",
    "searchQuery" : "rig",
    "searchInteractionURIs" : [
      ""
    ]
  },
  {
    "platform" : "ANDROID",
    "searchTime" : "2019-11-30T06:18:00.590Z[UTC]",
    "searchQuery" : "riga",
    "searchInteractionURIs" : [
      ""
    ]
  },
  {
    "platform" : "ANDROID",
    "searchTime" : "2019-11-30T06:18:06.733Z[UTC]",
    "searchQuery" : "rih",
    "searchInteractionURIs" : [
      ""
    ]
  },
  {
    "platform" : "ANDROID",
    "searchTime" : "2019-11-30T06:18:08.189Z[UTC]",
    "searchQuery" : "co si",
    "searchInteractionURIs" : [
      ""
    ]
  },
  {
    "platform" : "ANDROID",
    "searchTime" : "2019-11-30T06:18:10.991Z[UTC]",
    "searchQuery" : "con",
    "searchInteractionURIs" : [
      ""
    ]
  },
  {
    "platform" : "ANDROID",
    "searchTime" : "2019-11-30T06:18:11.631Z[UTC]",
    "searchQuery" : "consd",
    "searchInteractionURIs" : [
      "spotify:track:6t90Z9XkdsHD8xMxro6KRP"
    ]
  },
  {
    "platform" : "ANDROID",
    "searchTime" : "2019-11-30T06:20:42.848Z[UTC]",
    "searchQuery" : "cons",
    "searchInteractionURIs" : [
      ""
    ]
  },
  {
    "platform" : "ANDROID",
    "searchTime" : "2019-11-30T06:20:44.736Z[UTC]",
    "searchQuery" : "wprk",
    "searchInteractionURIs" : [
      "spotify:track:72TFWvU3wUYdUuxejTTIzt",
      "spotify:track:72TFWvU3wUYdUuxejTTIzt"
    ]
  },
  {
    "platform" : "ANDROID",
    "searchTime" : "2019-11-30T09:25:28.791Z[UTC]",
    "searchQuery" : "mi gusta",
    "searchInteractionURIs" : [
      "spotify:playlist:63U6teeDI5RJsRSmGWhcAR",
      "spotify:track:6b37xrsNCWYIUphFBazqD6"
    ]
  },
  {
    "platform" : "ANDROID",
    "searchTime" : "2019-11-30T09:29:50.315Z[UTC]",
    "searchQuery" : "m",
    "searchInteractionURIs" : [
      ""
    ]
  },
  {
    "platform" : "ANDROID",
    "searchTime" : "2019-11-30T09:29:53.560Z[UTC]",
    "searchQuery" : "bongo",
    "searchInteractionURIs" : [
      "spotify:track:00SmB7n85SKROGjybsyq5i"
    ]
  },
  {
    "platform" : "ANDROID",
    "searchTime" : "2019-12-04T09:55:44.042Z[UTC]",
    "searchQuery" : "Cupid's Chokehold Gym Class Heroes",
    "searchInteractionURIs" : [
      "spotify:track:2Lhdl74nwwVGOE2Gv35QuK"
    ]
  },
  {
    "platform" : "ANDROID",
    "searchTime" : "2019-12-04T09:56:46.887Z[UTC]",
    "searchQuery" : "Get Away BJ the Chicago Kid",
    "searchInteractionURIs" : [
      "spotify:track:0sfDMsYTbwKYNSqd7SPqRn",
      ""
    ]
  },
  {
    "platform" : "ANDROID",
    "searchTime" : "2019-12-05T08:07:43.727Z[UTC]",
    "searchQuery" : "swim good",
    "searchInteractionURIs" : [
    ]
  },
  {
    "platform" : "ANDROID",
    "searchTime" : "2019-12-06T01:55:17.651Z[UTC]",
    "searchQuery" : "solita",
    "searchInteractionURIs" : [
      "spotify:album:1SvuC2OLkAJnuNhZNDohIR"
    ]
  },
  {
    "platform" : "DESKTOP",
    "searchTime" : "2019-12-06T04:56:27.362Z[UTC]",
    "searchQuery" : "fields of blue",
    "searchInteractionURIs" : [
      "spotify:track:4NycjftFBqKHOmBmZcbxry"
    ]
  },
  {
    "platform" : "DESKTOP",
    "searchTime" : "2019-12-06T05:05:49.879Z[UTC]",
    "searchQuery" : "fields of blue ",
    "searchInteractionURIs" : [
    ]
  },
  {
    "platform" : "DESKTOP",
    "searchTime" : "2019-12-06T22:50:07.402Z[UTC]",
    "searchQuery" : "fields of blue ow",
    "searchInteractionURIs" : [
    ]
  },
  {
    "platform" : "DESKTOP",
    "searchTime" : "2019-12-07T09:53:20.046Z[UTC]",
    "searchQuery" : "fields of blue ow",
    "searchInteractionURIs" : [
    ]
  },
  {
    "platform" : "DESKTOP",
    "searchTime" : "2019-12-07T20:02:12.954Z[UTC]",
    "searchQuery" : "fields of blue ow",
    "searchInteractionURIs" : [
    ]
  },
  {
    "platform" : "DESKTOP",
    "searchTime" : "2019-12-07T21:18:39.050Z[UTC]",
    "searchQuery" : "fields of blue ow",
    "searchInteractionURIs" : [
    ]
  },
  {
    "platform" : "ANDROID",
    "searchTime" : "2019-12-09T07:40:49.728Z[UTC]",
    "searchQuery" : "mr",
    "searchInteractionURIs" : [
      ""
    ]
  },
  {
    "platform" : "ANDROID",
    "searchTime" : "2019-12-09T07:40:52.602Z[UTC]",
    "searchQuery" : "bongo",
    "searchInteractionURIs" : [
      "spotify:track:00SmB7n85SKROGjybsyq5i"
    ]
  },
  {
    "platform" : "ANDROID",
    "searchTime" : "2019-12-09T07:43:07.034Z[UTC]",
    "searchQuery" : "paper p",
    "searchInteractionURIs" : [
    ]
  },
  {
    "platform" : "ANDROID",
    "searchTime" : "2019-12-09T07:44:57.385Z[UTC]",
    "searchQuery" : "goose",
    "searchInteractionURIs" : [
      "spotify:track:6gBFPUFcJLzWGx4lenP6h2"
    ]
  },
  {
    "platform" : "ANDROID",
    "searchTime" : "2019-12-09T07:45:10.562Z[UTC]",
    "searchQuery" : "go",
    "searchInteractionURIs" : [
      ""
    ]
  },
  {
    "platform" : "ANDROID",
    "searchTime" : "2019-12-09T07:45:13.175Z[UTC]",
    "searchQuery" : "love",
    "searchInteractionURIs" : [
      "spotify:track:6PGoSes0D9eUDeeAafB2As"
    ]
  },
  {
    "platform" : "ANDROID",
    "searchTime" : "2019-12-09T07:45:29.642Z[UTC]",
    "searchQuery" : "lo",
    "searchInteractionURIs" : [
      ""
    ]
  },
  {
    "platform" : "ANDROID",
    "searchTime" : "2019-12-09T07:45:39.106Z[UTC]",
    "searchQuery" : "hips dont",
    "searchInteractionURIs" : [
      "spotify:track:3ZFTkvIE7kyPt6Nu3PEa7V",
      "spotify:track:3ZFTkvIE7kyPt6Nu3PEa7V"
    ]
  },
  {
    "platform" : "ANDROID",
    "searchTime" : "2019-12-09T07:49:23.557Z[UTC]",
    "searchQuery" : "hi",
    "searchInteractionURIs" : [
      ""
    ]
  },
  {
    "platform" : "ANDROID",
    "searchTime" : "2019-12-09T07:49:34.428Z[UTC]",
    "searchQuery" : "whatev",
    "searchInteractionURIs" : [
      ""
    ]
  },
  {
    "platform" : "ANDROID",
    "searchTime" : "2019-12-09T07:49:36.388Z[UTC]",
    "searchQuery" : "whenever w",
    "searchInteractionURIs" : [
      "spotify:track:2lnzGkdtDj5mtlcOW2yRtG",
      "spotify:playlist:5peD3ZrvVFJwHuWTiAFD11"
    ]
  },
  {
    "platform" : "ANDROID",
    "searchTime" : "2019-12-09T07:52:35.041Z[UTC]",
    "searchQuery" : "britney speakrs my pero mlm",
    "searchInteractionURIs" : [
    ]
  },
  {
    "platform" : "ANDROID",
    "searchTime" : "2019-12-09T07:52:36.221Z[UTC]",
    "searchQuery" : "britney speakrs",
    "searchInteractionURIs" : [
      ""
    ]
  },
  {
    "platform" : "ANDROID",
    "searchTime" : "2019-12-09T07:52:41.213Z[UTC]",
    "searchQuery" : "my perogavtive",
    "searchInteractionURIs" : [
      "spotify:track:2TxLSV0AqZTYQQL9QCX0D4"
    ]
  },
  {
    "platform" : "ANDROID",
    "searchTime" : "2019-12-09T07:52:48.156Z[UTC]",
    "searchQuery" : "my p",
    "searchInteractionURIs" : [
      ""
    ]
  },
  {
    "platform" : "ANDROID",
    "searchTime" : "2019-12-09T07:52:53.666Z[UTC]",
    "searchQuery" : "britney s",
    "searchInteractionURIs" : [
      "spotify:artist:26dSoYclwsYLMAKD3tpOr4"
    ]
  },
  {
    "platform" : "ANDROID",
    "searchTime" : "2019-12-09T07:53:57.950Z[UTC]",
    "searchQuery" : "piece of me",
    "searchInteractionURIs" : [
      "spotify:track:2EvwLVrnYbCZEG6Kx5DCRy",
      "spotify:track:5CbcqhKsBbiOsjdkh5Hsea"
    ]
  },
  {
    "platform" : "ANDROID",
    "searchTime" : "2019-12-09T07:58:08.905Z[UTC]",
    "searchQuery" : "piece of me britn",
    "searchInteractionURIs" : [
      "spotify:track:2EvwLVrnYbCZEG6Kx5DCRy"
    ]
  },
  {
    "platform" : "ANDROID",
    "searchTime" : "2019-12-09T08:07:02.188Z[UTC]",
    "searchQuery" : "yeah uehet",
    "searchInteractionURIs" : [
    ]
  },
  {
    "platform" : "ANDROID",
    "searchTime" : "2019-12-09T08:07:04.780Z[UTC]",
    "searchQuery" : "yea",
    "searchInteractionURIs" : [
      ""
    ]
  },
  {
    "platform" : "ANDROID",
    "searchTime" : "2019-12-09T08:07:20.408Z[UTC]",
    "searchQuery" : "nqke love in this club ",
    "searchInteractionURIs" : [
      "spotify:playlist:0ZUvY5YVVgMR1nx5vfpfqc"
    ]
  },
  {
    "platform" : "ANDROID",
    "searchTime" : "2019-12-09T08:07:30.268Z[UTC]",
    "searchQuery" : "nqke ",
    "searchInteractionURIs" : [
      ""
    ]
  },
  {
    "platform" : "ANDROID",
    "searchTime" : "2019-12-09T08:07:33.482Z[UTC]",
    "searchQuery" : "love in this ckib",
    "searchInteractionURIs" : [
      "spotify:track:5j0McHPthKpOXRr3fBq8M0",
      ""
    ]
  },
  {
    "platform" : "ANDROID",
    "searchTime" : "2019-12-09T08:13:41.953Z[UTC]",
    "searchQuery" : "paper pla",
    "searchInteractionURIs" : [
      "spotify:track:1kusepF3AacIEtUTYrw4GV"
    ]
  },
  {
    "platform" : "ANDROID",
    "searchTime" : "2019-12-09T10:37:56.996Z[UTC]",
    "searchQuery" : "khaliabli",
    "searchInteractionURIs" : [
      "spotify:track:6sXzqMagXtWvSOI9nNc4UD"
    ]
  },
  {
    "platform" : "ANDROID",
    "searchTime" : "2019-12-09T10:44:59.119Z[UTC]",
    "searchQuery" : "k",
    "searchInteractionURIs" : [
      ""
    ]
  },
  {
    "platform" : "DESKTOP",
    "searchTime" : "2019-12-09T13:36:07.275Z[UTC]",
    "searchQuery" : "fields of blue ow",
    "searchInteractionURIs" : [
    ]
  },
  {
    "platform" : "DESKTOP",
    "searchTime" : "2019-12-09T17:30:49.966Z[UTC]",
    "searchQuery" : "fields of blue ow",
    "searchInteractionURIs" : [
    ]
  },
  {
    "platform" : "DESKTOP",
    "searchTime" : "2019-12-09T22:04:27.982Z[UTC]",
    "searchQuery" : "fields of blue ow",
    "searchInteractionURIs" : [
    ]
  },
  {
    "platform" : "DESKTOP",
    "searchTime" : "2019-12-10T00:31:32.579Z[UTC]",
    "searchQuery" : "fields of blue ow",
    "searchInteractionURIs" : [
    ]
  },
  {
    "platform" : "DESKTOP",
    "searchTime" : "2019-12-14T05:21:27.690Z[UTC]",
    "searchQuery" : "the internet",
    "searchInteractionURIs" : [
      "spotify:track:300DUx4tdtCdGEUXR032jA"
    ]
  },
  {
    "platform" : "DESKTOP",
    "searchTime" : "2019-12-14T06:14:21.231Z[UTC]",
    "searchQuery" : "japanese",
    "searchInteractionURIs" : [
      "spotify:track:1boXOL0ua7N2iCOUVI1p9F"
    ]
  },
  {
    "platform" : "DESKTOP",
    "searchTime" : "2019-12-14T06:33:15.337Z[UTC]",
    "searchQuery" : "running out of time",
    "searchInteractionURIs" : [
      "spotify:track:5QvBXUm5MglLJ3iBfTX2Wo"
    ]
  },
  {
    "platform" : "ANDROID",
    "searchTime" : "2019-12-17T05:34:26.218Z[UTC]",
    "searchQuery" : "gully",
    "searchInteractionURIs" : [
      "spotify:album:3UhZwBv1QvSLG1OFQXx930"
    ]
  },
  {
    "platform" : "ANDROID",
    "searchTime" : "2019-12-17T05:40:19.827Z[UTC]",
    "searchQuery" : "gully",
    "searchInteractionURIs" : [
      "spotify:album:3UhZwBv1QvSLG1OFQXx930"
    ]
  },
  {
    "platform" : "ANDROID",
    "searchTime" : "2019-12-17T05:44:09.760Z[UTC]",
    "searchQuery" : "e",
    "searchInteractionURIs" : [
    ]
  },
  {
    "platform" : "ANDROID",
    "searchTime" : "2019-12-17T05:44:14.378Z[UTC]",
    "searchQuery" : "paper",
    "searchInteractionURIs" : [
      "spotify:track:1kusepF3AacIEtUTYrw4GV",
      ""
    ]
  },
  {
    "platform" : "ANDROID",
    "searchTime" : "2019-12-17T06:33:18.687Z[UTC]",
    "searchQuery" : "gully",
    "searchInteractionURIs" : [
      "spotify:album:3UhZwBv1QvSLG1OFQXx930"
    ]
  },
  {
    "platform" : "ANDROID",
    "searchTime" : "2019-12-17T06:42:16.553Z[UTC]",
    "searchQuery" : "gully",
    "searchInteractionURIs" : [
    ]
  },
  {
    "platform" : "ANDROID",
    "searchTime" : "2019-12-17T07:29:56.533Z[UTC]",
    "searchQuery" : "divine",
    "searchInteractionURIs" : [
      "spotify:artist:4Ai0pGz6GhQavjzaRhPTvz"
    ]
  },
  {
    "platform" : "ANDROID",
    "searchTime" : "2019-12-17T07:32:21Z[UTC]",
    "searchQuery" : "bo",
    "searchInteractionURIs" : [
      ""
    ]
  },
  {
    "platform" : "ANDROID",
    "searchTime" : "2019-12-17T07:33:21.693Z[UTC]",
    "searchQuery" : "bomgay ",
    "searchInteractionURIs" : [
      "spotify:search:tracks:bomgay%20"
    ]
  },
  {
    "platform" : "ANDROID",
    "searchTime" : "2019-12-17T07:33:29.538Z[UTC]",
    "searchQuery" : "bomgay ",
    "searchInteractionURIs" : [
      "spotify:track:6AooRgSRDzbCYL4NZ4RCjU"
    ]
  },
  {
    "platform" : "ANDROID",
    "searchTime" : "2019-12-17T07:35:31.814Z[UTC]",
    "searchQuery" : "bomgay ",
    "searchInteractionURIs" : [
    ]
  },
  {
    "platform" : "ANDROID",
    "searchTime" : "2019-12-17T07:59:44.042Z[UTC]",
    "searchQuery" : "gully boy",
    "searchInteractionURIs" : [
      "spotify:album:3UhZwBv1QvSLG1OFQXx930"
    ]
  },
  {
    "platform" : "ANDROID",
    "searchTime" : "2019-12-17T09:00:17.992Z[UTC]",
    "searchQuery" : "a r rahman",
    "searchInteractionURIs" : [
      "spotify:artist:1mYsTxnqsietFxj1OgoGbG"
    ]
  },
  {
    "platform" : "ANDROID",
    "searchTime" : "2019-12-17T09:03:00.691Z[UTC]",
    "searchQuery" : "gur",
    "searchInteractionURIs" : [
      ""
    ]
  },
  {
    "platform" : "ANDROID",
    "searchTime" : "2019-12-17T09:03:02.256Z[UTC]",
    "searchQuery" : "gur",
    "searchInteractionURIs" : [
      ""
    ]
  },
  {
    "platform" : "ANDROID",
    "searchTime" : "2019-12-17T09:03:05.011Z[UTC]",
    "searchQuery" : "ay",
    "searchInteractionURIs" : [
      ""
    ]
  },
  {
    "platform" : "ANDROID",
    "searchTime" : "2019-12-17T09:03:05.641Z[UTC]",
    "searchQuery" : "a",
    "searchInteractionURIs" : [
      ""
    ]
  },
  {
    "platform" : "ANDROID",
    "searchTime" : "2019-12-17T09:03:07.252Z[UTC]",
    "searchQuery" : "guru",
    "searchInteractionURIs" : [
      "spotify:album:6kWI9GDPhMhaGNo80Q1XT5"
    ]
  },
  {
    "platform" : "ANDROID",
    "searchTime" : "2019-12-19T11:53:52.940Z[UTC]",
    "searchQuery" : "right here tight now",
    "searchInteractionURIs" : [
      "spotify:search:tracks:right%20here%20tight%20now"
    ]
  },
  {
    "platform" : "ANDROID",
    "searchTime" : "2019-12-19T11:53:56.384Z[UTC]",
    "searchQuery" : "right here tight now",
    "searchInteractionURIs" : [
      "spotify:track:4pVnxSz312uhq2hM3b8CAO"
    ]
  },
  {
    "platform" : "ANDROID",
    "searchTime" : "2019-12-24T19:12:04.078Z[UTC]",
    "searchQuery" : "queen",
    "searchInteractionURIs" : [
      "spotify:playlist:37i9dQZF1DWSNC7AjZWNry",
      "spotify:artist:1dfeR4HaWDbWqFHLkxsg1d",
      "spotify:playlist:37i9dQZF1DWSNC7AjZWNry"
    ]
  },
  {
    "platform" : "ANDROID",
    "searchTime" : "2019-12-24T20:50:41.094Z[UTC]",
    "searchQuery" : "geto boys",
    "searchInteractionURIs" : [
      "spotify:artist:3f5fB1YUbkUnW7cf7I0R48"
    ]
  },
  {
    "platform" : "ANDROID",
    "searchTime" : "2019-12-24T22:19:22.170Z[UTC]",
    "searchQuery" : "jingo",
    "searchInteractionURIs" : [
      "spotify:track:06ECyIQclBsjerzJsEerTY"
    ]
  },
  {
    "platform" : "ANDROID",
    "searchTime" : "2019-12-25T01:41:11.272Z[UTC]",
    "searchQuery" : "i said hey",
    "searchInteractionURIs" : [
    ]
  },
  {
    "platform" : "ANDROID",
    "searchTime" : "2019-12-25T01:41:15.260Z[UTC]",
    "searchQuery" : "i s",
    "searchInteractionURIs" : [
      ""
    ]
  },
  {
    "platform" : "ANDROID",
    "searchTime" : "2019-12-25T01:41:19.845Z[UTC]",
    "searchQuery" : "f",
    "searchInteractionURIs" : [
      ""
    ]
  },
  {
    "platform" : "ANDROID",
    "searchTime" : "2019-12-25T01:41:20.889Z[UTC]",
    "searchQuery" : "c",
    "searchInteractionURIs" : [
      ""
    ]
  },
  {
    "platform" : "ANDROID",
    "searchTime" : "2019-12-25T01:41:22.688Z[UTC]",
    "searchQuery" : "santana",
    "searchInteractionURIs" : [
      "spotify:artist:6GI52t8N5F02MxU0g5U69P"
    ]
  },
  {
    "platform" : "ANDROID",
    "searchTime" : "2019-12-25T01:42:27.738Z[UTC]",
    "searchQuery" : "say hey",
    "searchInteractionURIs" : [
      "spotify:track:0nnxf8p851ZR49KFnGWVsB",
      "spotify:track:0nnxf8p851ZR49KFnGWVsB"
    ]
  },
  {
    "platform" : "ANDROID",
    "searchTime" : "2019-12-25T01:45:59.059Z[UTC]",
    "searchQuery" : "mind",
    "searchInteractionURIs" : [
      "spotify:track:63BokRfXSQhEU6Qi2dSJpZ"
    ]
  },
  {
    "platform" : "ANDROID",
    "searchTime" : "2019-12-25T03:57:35.888Z[UTC]",
    "searchQuery" : "som",
    "searchInteractionURIs" : [
      ""
    ]
  },
  {
    "platform" : "ANDROID",
    "searchTime" : "2019-12-25T03:57:36.014Z[UTC]",
    "searchQuery" : "some",
    "searchInteractionURIs" : [
      ""
    ]
  },
  {
    "platform" : "ANDROID",
    "searchTime" : "2019-12-25T03:57:38.658Z[UTC]",
    "searchQuery" : "sometimes",
    "searchInteractionURIs" : [
      "spotify:track:7oJmIBxEAYjfkS7lhZ7M1S"
    ]
  },
  {
    "platform" : "ANDROID",
    "searchTime" : "2019-12-25T20:45:42.680Z[UTC]",
    "searchQuery" : "being ",
    "searchInteractionURIs" : [
      "spotify:track:4GDSnxxtmIyVS4Twl7Y7UB"
    ]
  },
  {
    "platform" : "ANDROID",
    "searchTime" : "2019-12-25T20:45:59.362Z[UTC]",
    "searchQuery" : "being alive adam driver",
    "searchInteractionURIs" : [
      "spotify:playlist:1fdk69xHXqYkLPPPuXV0BW"
    ]
  },
  {
    "platform" : "ANDROID",
    "searchTime" : "2019-12-27T05:29:22.857Z[UTC]",
    "searchQuery" : "don toli",
    "searchInteractionURIs" : [
      "spotify:artist:4Gso3d4CscCijv0lmajZWs"
    ]
  },
  {
    "platform" : "ANDROID",
    "searchTime" : "2019-12-28T18:40:03.537Z[UTC]",
    "searchQuery" : "sweet",
    "searchInteractionURIs" : [
      "spotify:track:2DgMxFMUQRPthW4ROhjen1"
    ]
  },
  {
    "platform" : "ANDROID",
    "searchTime" : "2019-12-28T18:41:58.546Z[UTC]",
    "searchQuery" : "sweet ",
    "searchInteractionURIs" : [
      ""
    ]
  },
  {
    "platform" : "ANDROID",
    "searchTime" : "2019-12-31T05:53:46.841Z[UTC]",
    "searchQuery" : "wonder",
    "searchInteractionURIs" : [
      "spotify:track:5wj4E6IsrVtn8IBJQOd0Cl",
      ""
    ]
  },
  {
    "platform" : "ANDROID",
    "searchTime" : "2019-12-31T05:58:18.161Z[UTC]",
    "searchQuery" : "orher",
    "searchInteractionURIs" : [
      "spotify:track:64BbK9SFKH2jk86U3dGj2P"
    ]
  },
  {
    "platform" : "ANDROID",
    "searchTime" : "2019-12-31T06:00:19.691Z[UTC]",
    "searchQuery" : "m",
    "searchInteractionURIs" : [
      ""
    ]
  },
  {
    "platform" : "ANDROID",
    "searchTime" : "2019-12-31T06:00:21.763Z[UTC]",
    "searchQuery" : "maad ",
    "searchInteractionURIs" : [
      "spotify:track:2cDCojn6uIBM6A5xTAbl3H"
    ]
  },
  {
    "platform" : "ANDROID",
    "searchTime" : "2019-12-31T06:03:46.053Z[UTC]",
    "searchQuery" : "mind",
    "searchInteractionURIs" : [
      "spotify:track:63BokRfXSQhEU6Qi2dSJpZ",
      "spotify:album:5amj9zNeZ3B2EdpBgXrOZ0"
    ]
  },
  {
    "platform" : "ANDROID",
    "searchTime" : "2019-12-31T06:54:57.631Z[UTC]",
    "searchQuery" : "saiba",
    "searchInteractionURIs" : [
      "spotify:search:tracks:saiba"
    ]
  },
  {
    "platform" : "ANDROID",
    "searchTime" : "2019-12-31T06:55:19.673Z[UTC]",
    "searchQuery" : "m",
    "searchInteractionURIs" : [
      ""
    ]
  },
  {
    "platform" : "ANDROID",
    "searchTime" : "2019-12-31T06:55:28.107Z[UTC]",
    "searchQuery" : "ma",
    "searchInteractionURIs" : [
      ""
    ]
  },
  {
    "platform" : "ANDROID",
    "searchTime" : "2019-12-31T06:55:34.785Z[UTC]",
    "searchQuery" : "guzaa",
    "searchInteractionURIs" : [
      "spotify:album:5aNyDyemGpcaJGMuLvUife"
    ]
  },
  {
    "platform" : "ANDROID",
    "searchTime" : "2019-12-31T07:02:59.467Z[UTC]",
    "searchQuery" : "gu",
    "searchInteractionURIs" : [
      ""
    ]
  },
  {
    "platform" : "ANDROID",
    "searchTime" : "2019-12-31T07:03:00.947Z[UTC]",
    "searchQuery" : "dev",
    "searchInteractionURIs" : [
      ""
    ]
  },
  {
    "platform" : "ANDROID",
    "searchTime" : "2019-12-31T07:03:02.885Z[UTC]",
    "searchQuery" : "devdaa",
    "searchInteractionURIs" : [
      "spotify:playlist:5HcpUqyGPOBIlgpJA6beJ4"
    ]
  },
  {
    "platform" : "ANDROID",
    "searchTime" : "2019-12-31T07:39:58.610Z[UTC]",
    "searchQuery" : "A ",
    "searchInteractionURIs" : [
      ""
    ]
  },
  {
    "platform" : "ANDROID",
    "searchTime" : "2019-12-31T07:40:01.272Z[UTC]",
    "searchQuery" : "a r r",
    "searchInteractionURIs" : [
      ""
    ]
  },
  {
    "platform" : "ANDROID",
    "searchTime" : "2019-12-31T07:40:01.657Z[UTC]",
    "searchQuery" : "a r ra",
    "searchInteractionURIs" : [
      "spotify:artist:1mYsTxnqsietFxj1OgoGbG",
      "spotify:playlist:1xFLokzIyS2u6dX4rcFPAr"
    ]
  },
  {
    "platform" : "ANDROID",
    "searchTime" : "2019-12-31T21:00:52.058Z[UTC]",
    "searchQuery" : "Entropy Grimes",
    "searchInteractionURIs" : [
      "spotify:track:5li3FHS5s9V3l4xWsUcmQa"
    ]
  },
  {
    "platform" : "ANDROID",
    "searchTime" : "2019-12-31T23:57:36.112Z[UTC]",
    "searchQuery" : "Entropy Grimes",
    "searchInteractionURIs" : [
      "spotify:track:5li3FHS5s9V3l4xWsUcmQa"
    ]
  },
  {
    "platform" : "ANDROID",
    "searchTime" : "2020-01-01T06:13:06.793Z[UTC]",
    "searchQuery" : "kendr",
    "searchInteractionURIs" : [
      "spotify:artist:2YZyLoL8N0Wb9xBt1NhZWg"
    ]
  },
  {
    "platform" : "ANDROID",
    "searchTime" : "2020-01-03T00:19:26.453Z[UTC]",
    "searchQuery" : "psy",
    "searchInteractionURIs" : [
      "spotify:track:3swc6WTsr7rl9DqQKQA55C"
    ]
  },
  {
    "platform" : "ANDROID",
    "searchTime" : "2020-01-03T00:19:39.369Z[UTC]",
    "searchQuery" : "psycho killer",
    "searchInteractionURIs" : [
      "spotify:track:1i6N76fftMZhijOzFQ5ZtL"
    ]
  },
  {
    "platform" : "ANDROID",
    "searchTime" : "2020-01-03T07:24:06.347Z[UTC]",
    "searchQuery" : "brit",
    "searchInteractionURIs" : [
      "spotify:artist:26dSoYclwsYLMAKD3tpOr4"
    ]
  },
  {
    "platform" : "ANDROID",
    "searchTime" : "2020-01-03T22:10:51.797Z[UTC]",
    "searchQuery" : "w",
    "searchInteractionURIs" : [
      ""
    ]
  },
  {
    "platform" : "ANDROID",
    "searchTime" : "2020-01-03T22:10:53.095Z[UTC]",
    "searchQuery" : "queen",
    "searchInteractionURIs" : [
      "spotify:artist:1dfeR4HaWDbWqFHLkxsg1d"
    ]
  },
  {
    "platform" : "ANDROID",
    "searchTime" : "2020-01-03T23:21:03.051Z[UTC]",
    "searchQuery" : "dont",
    "searchInteractionURIs" : [
      "spotify:track:7hQJA50XrCWABAu5v6QZ4i"
    ]
  },
  {
    "platform" : "DESKTOP",
    "searchTime" : "2020-01-06T00:15:26.515Z[UTC]",
    "searchQuery" : "to be with you",
    "searchInteractionURIs" : [
      "spotify:track:3bP47tw8MOgtrwdO1iahVl"
    ]
  },
  {
    "platform" : "DESKTOP",
    "searchTime" : "2020-01-06T00:18:59.269Z[UTC]",
    "searchQuery" : "some g",
    "searchInteractionURIs" : [
      "spotify:track:6wOdpwaVrRtWlVSQNMBNQU"
    ]
  },
  {
    "platform" : "DESKTOP",
    "searchTime" : "2020-01-06T00:24:36.450Z[UTC]",
    "searchQuery" : "steve ",
    "searchInteractionURIs" : [
      "spotify:artist:57vWImR43h4CaDao012Ofp"
    ]
  },
  {
    "platform" : "ANDROID",
    "searchTime" : "2020-01-09T00:53:08.355Z[UTC]",
    "searchQuery" : "a",
    "searchInteractionURIs" : [
      ""
    ]
  },
  {
    "platform" : "ANDROID",
    "searchTime" : "2020-01-09T00:53:09.220Z[UTC]",
    "searchQuery" : "sand",
    "searchInteractionURIs" : [
      "spotify:track:1NlWBpNYAnFT7gMGyC0Y1M"
    ]
  },
  {
    "platform" : "ANDROID",
    "searchTime" : "2020-01-10T01:48:31.574Z[UTC]",
    "searchQuery" : "cant",
    "searchInteractionURIs" : [
      "spotify:track:27a1mYSG5tYg7dmEjWBcmL"
    ]
  },
  {
    "platform" : "ANDROID",
    "searchTime" : "2020-01-11T07:19:39.458Z[UTC]",
    "searchQuery" : "khalbali",
    "searchInteractionURIs" : [
      "spotify:track:6sXzqMagXtWvSOI9nNc4UD",
      "spotify:track:6sXzqMagXtWvSOI9nNc4UD",
      "spotify:track:6sXzqMagXtWvSOI9nNc4UD"
    ]
  },
  {
    "platform" : "ANDROID",
    "searchTime" : "2020-01-11T07:32:28.562Z[UTC]",
    "searchQuery" : "a r rahman",
    "searchInteractionURIs" : [
      "spotify:artist:1mYsTxnqsietFxj1OgoGbG"
    ]
  },
  {
    "platform" : "ANDROID",
    "searchTime" : "2020-01-11T07:36:36.361Z[UTC]",
    "searchQuery" : "banarisa",
    "searchInteractionURIs" : [
    ]
  },
  {
    "platform" : "ANDROID",
    "searchTime" : "2020-01-11T07:36:42.458Z[UTC]",
    "searchQuery" : "b",
    "searchInteractionURIs" : [
      ""
    ]
  },
  {
    "platform" : "ANDROID",
    "searchTime" : "2020-01-11T07:36:47.514Z[UTC]",
    "searchQuery" : "a r rahman",
    "searchInteractionURIs" : [
      "spotify:artist:1mYsTxnqsietFxj1OgoGbG"
    ]
  },
  {
    "platform" : "ANDROID",
    "searchTime" : "2020-01-11T07:40:17.074Z[UTC]",
    "searchQuery" : "a r rahman",
    "searchInteractionURIs" : [
      "spotify:artist:1mYsTxnqsietFxj1OgoGbG"
    ]
  },
  {
    "platform" : "ANDROID",
    "searchTime" : "2020-01-14T05:35:21.083Z[UTC]",
    "searchQuery" : "hozier",
    "searchInteractionURIs" : [
      "spotify:artist:2FXC3k01G6Gw61bmprjgqS"
    ]
  },
  {
    "platform" : "ANDROID",
    "searchTime" : "2020-01-15T03:05:08.534Z[UTC]",
    "searchQuery" : "invite",
    "searchInteractionURIs" : [
      "spotify:track:6vvwto0FBmtxEIOiNpBFff"
    ]
  },
  {
    "platform" : "ANDROID",
    "searchTime" : "2020-01-15T03:10:35.962Z[UTC]",
    "searchQuery" : "right here right now",
    "searchInteractionURIs" : [
      "spotify:search:tracks:right%20here%20right%20now"
    ]
  },
  {
    "platform" : "ANDROID",
    "searchTime" : "2020-01-15T03:10:39.162Z[UTC]",
    "searchQuery" : "right here right now",
    "searchInteractionURIs" : [
      "spotify:track:4pVnxSz312uhq2hM3b8CAO"
    ]
  },
  {
    "platform" : "ANDROID",
    "searchTime" : "2020-01-16T03:26:06.816Z[UTC]",
    "searchQuery" : "foight",
    "searchInteractionURIs" : [
      "spotify:track:3iv26BUAWSn83q8rhGKPE8"
    ]
  },
  {
    "platform" : "ANDROID",
    "searchTime" : "2020-01-18T23:38:29.457Z[UTC]",
    "searchQuery" : "aaj ",
    "searchInteractionURIs" : [
      ""
    ]
  },
  {
    "platform" : "ANDROID",
    "searchTime" : "2020-01-19T04:14:04.650Z[UTC]",
    "searchQuery" : "kaisi ha",
    "searchInteractionURIs" : [
      "spotify:track:4x6hxkEuw1XLIwUkUJcDbf"
    ]
  },
  {
    "platform" : "ANDROID",
    "searchTime" : "2020-01-19T04:20:21.790Z[UTC]",
    "searchQuery" : "kaisi ha ",
    "searchInteractionURIs" : [
    ]
  },
  {
    "platform" : "ANDROID",
    "searchTime" : "2020-01-19T04:29:05.123Z[UTC]",
    "searchQuery" : "kaisi ha .",
    "searchInteractionURIs" : [
    ]
  },
  {
    "platform" : "ANDROID",
    "searchTime" : "2020-01-19T22:39:47.994Z[UTC]",
    "searchQuery" : "i am",
    "searchInteractionURIs" : [
      "spotify:track:0DJBgBiYeSn6n1AXAkFVE8"
    ]
  },
  {
    "platform" : "ANDROID",
    "searchTime" : "2020-01-19T22:43:34.460Z[UTC]",
    "searchQuery" : "isol",
    "searchInteractionURIs" : [
      "spotify:album:4EPQtdq6vvwxuYeQTrwDVY"
    ]
  },
  {
    "platform" : "ANDROID",
    "searchTime" : "2020-01-19T23:53:53.989Z[UTC]",
    "searchQuery" : "leaf clov",
    "searchInteractionURIs" : [
      "spotify:track:1To829onYmL63wLNtU7Zm8",
      "spotify:track:7EVRvvmpDvPbWyLAk1NRsH",
      "spotify:track:1To829onYmL63wLNtU7Zm8"
    ]
  },
  {
    "platform" : "ANDROID",
    "searchTime" : "2020-01-20T01:08:18.214Z[UTC]",
    "searchQuery" : "leaf clov,",
    "searchInteractionURIs" : [
    ]
  },
  {
    "platform" : "ANDROID",
    "searchTime" : "2020-01-20T01:10:58.648Z[UTC]",
    "searchQuery" : "leaf clov, ",
    "searchInteractionURIs" : [
    ]
  },
  {
    "platform" : "ANDROID",
    "searchTime" : "2020-01-20T01:37:59.393Z[UTC]",
    "searchQuery" : "wildin",
    "searchInteractionURIs" : [
      "spotify:track:4LGg2NY9eHp0jF3L1WbCNl"
    ]
  },
  {
    "platform" : "ANDROID",
    "searchTime" : "2020-01-20T01:43:07.775Z[UTC]",
    "searchQuery" : "circle",
    "searchInteractionURIs" : [
      "spotify:track:4jXl6VtkFFKIt3ycUQc5LT",
      "spotify:album:5sY6UIQ32GqwMLAfSNEaXb"
    ]
  },
  {
    "platform" : "ANDROID",
    "searchTime" : "2020-01-20T08:35:07.370Z[UTC]",
    "searchQuery" : "kay ser",
    "searchInteractionURIs" : [
      "spotify:track:0OXQa6GOzxeYWFopEmASw9"
    ]
  },
  {
    "platform" : "ANDROID",
    "searchTime" : "2020-01-20T21:32:11.745Z[UTC]",
    "searchQuery" : "blue world",
    "searchInteractionURIs" : [
      "spotify:track:2hwOoMtWPtTSSn6WHV7Vp5"
    ]
  },
  {
    "platform" : "DESKTOP",
    "searchTime" : "2020-01-22T02:20:26.141Z[UTC]",
    "searchQuery" : "make it better",
    "searchInteractionURIs" : [
      "spotify:track:4SBVWkRIMJ6WBCYPvr5Bwr"
    ]
  },
  {
    "platform" : "DESKTOP",
    "searchTime" : "2020-01-22T02:30:22.594Z[UTC]",
    "searchQuery" : "palace",
    "searchInteractionURIs" : [
      "spotify:track:300DUx4tdtCdGEUXR032jA"
    ]
  },
  {
    "platform" : "DESKTOP",
    "searchTime" : "2020-01-22T04:33:46.752Z[UTC]",
    "searchQuery" : "dicaprio2",
    "searchInteractionURIs" : [
      "spotify:album:2oI6gtIXrvNiL2VEMmj5kY"
    ]
  },
  {
    "platform" : "DESKTOP",
    "searchTime" : "2020-01-22T04:42:02.514Z[UTC]",
    "searchQuery" : "circles",
    "searchInteractionURIs" : [
      "spotify:album:5sY6UIQ32GqwMLAfSNEaXb"
    ]
  },
  {
    "platform" : "ANDROID",
    "searchTime" : "2020-01-23T10:28:10.899Z[UTC]",
    "searchQuery" : "wildin",
    "searchInteractionURIs" : [
      "spotify:track:4LGg2NY9eHp0jF3L1WbCNl"
    ]
  },
  {
    "platform" : "ANDROID",
    "searchTime" : "2020-01-23T11:25:47.429Z[UTC]",
    "searchQuery" : "gangs of",
    "searchInteractionURIs" : [
      "spotify:album:5lOKYvuSy6buolqIHSUwpG",
      "spotify:album:7DBbDXQbei6e4X6EdXOyz2",
      "spotify:album:5lOKYvuSy6buolqIHSUwpG",
      "spotify:album:7DBbDXQbei6e4X6EdXOyz2",
      "spotify:album:5lOKYvuSy6buolqIHSUwpG"
    ]
  },
  {
    "platform" : "ANDROID",
    "searchTime" : "2020-01-23T11:54:52.942Z[UTC]",
    "searchQuery" : "sneha",
    "searchInteractionURIs" : [
      "spotify:artist:3JtetEsoytPoOIPGvqUvSR"
    ]
  },
  {
    "platform" : "ANDROID",
    "searchTime" : "2020-01-23T11:59:20.208Z[UTC]",
    "searchQuery" : "husna",
    "searchInteractionURIs" : [
      "spotify:episode:6mGdysTlc1JguLiTd82f3M",
      "spotify:track:3TrFe0GKD2S2BLwqtpHqd5"
    ]
  },
  {
    "platform" : "ANDROID",
    "searchTime" : "2020-01-23T13:50:19.138Z[UTC]",
    "searchQuery" : "kaisi",
    "searchInteractionURIs" : [
      "spotify:track:4x6hxkEuw1XLIwUkUJcDbf"
    ]
  },
  {
    "platform" : "ANDROID",
    "searchTime" : "2020-01-24T01:14:09.933Z[UTC]",
    "searchQuery" : "ritvi",
    "searchInteractionURIs" : [
    ]
  },
  {
    "platform" : "DESKTOP",
    "searchTime" : "2020-01-26T00:05:27.269Z[UTC]",
    "searchQuery" : "raat raa",
    "searchInteractionURIs" : [
      "spotify:track:3k458zzqcF9UeRfZqRbZYr"
    ]
  },
  {
    "platform" : "DESKTOP",
    "searchTime" : "2020-01-26T01:16:19.283Z[UTC]",
    "searchQuery" : "danie",
    "searchInteractionURIs" : [
      "spotify:artist:20wkVLutqVOYrc0kxFs7rA"
    ]
  },
  {
    "platform" : "ANDROID",
    "searchTime" : "2020-01-26T07:41:27.041Z[UTC]",
    "searchQuery" : "daniel",
    "searchInteractionURIs" : [
      "spotify:artist:20wkVLutqVOYrc0kxFs7rA"
    ]
  },
  {
    "platform" : "ANDROID",
    "searchTime" : "2020-01-26T08:56:55.937Z[UTC]",
    "searchQuery" : "sweet",
    "searchInteractionURIs" : [
      "spotify:track:2DgMxFMUQRPthW4ROhjen1",
      "spotify:track:62AuGbAkt8Ox2IrFFb8GKV"
    ]
  },
  {
    "platform" : "ANDROID",
    "searchTime" : "2020-01-26T09:15:06.812Z[UTC]",
    "searchQuery" : "beautiful liar",
    "searchInteractionURIs" : [
      "spotify:track:2HWWNoWEEEECwZhAiLg7ib"
    ]
  },
  {
    "platform" : "ANDROID",
    "searchTime" : "2020-01-26T10:58:31.983Z[UTC]",
    "searchQuery" : "gangs of",
    "searchInteractionURIs" : [
      "spotify:album:5lOKYvuSy6buolqIHSUwpG"
    ]
  },
  {
    "platform" : "ANDROID",
    "searchTime" : "2020-01-26T11:14:51.834Z[UTC]",
    "searchQuery" : "a r rahman",
    "searchInteractionURIs" : [
      "spotify:artist:1mYsTxnqsietFxj1OgoGbG"
    ]
  },
  {
    "platform" : "ANDROID",
    "searchTime" : "2020-01-26T11:47:17.793Z[UTC]",
    "searchQuery" : "right he",
    "searchInteractionURIs" : [
      "spotify:track:4LFwNJWoj74Yd71fIr1W8x",
      "spotify:track:3Pb9QabepyR9e9D8NqorPH",
      ""
    ]
  },
  {
    "platform" : "ANDROID",
    "searchTime" : "2020-01-26T11:47:29.530Z[UTC]",
    "searchQuery" : "right here",
    "searchInteractionURIs" : [
      ""
    ]
  },
  {
    "platform" : "ANDROID",
    "searchTime" : "2020-01-26T11:47:30.198Z[UTC]",
    "searchQuery" : "right here ",
    "searchInteractionURIs" : [
      ""
    ]
  },
  {
    "platform" : "ANDROID",
    "searchTime" : "2020-01-26T11:47:31.603Z[UTC]",
    "searchQuery" : "right here ri",
    "searchInteractionURIs" : [
      "spotify:track:4pVnxSz312uhq2hM3b8CAO",
      "spotify:track:4pVnxSz312uhq2hM3b8CAO"
    ]
  },
  {
    "platform" : "ANDROID",
    "searchTime" : "2020-01-26T11:57:06.047Z[UTC]",
    "searchQuery" : "main ",
    "searchInteractionURIs" : [
      ""
    ]
  },
  {
    "platform" : "ANDROID",
    "searchTime" : "2020-01-26T11:57:09.722Z[UTC]",
    "searchQuery" : "main kya",
    "searchInteractionURIs" : [
      "spotify:track:4GagsETs7qfR3cwQkRcXgb"
    ]
  },
  {
    "platform" : "ANDROID",
    "searchTime" : "2020-01-26T13:03:13.957Z[UTC]",
    "searchQuery" : "moora",
    "searchInteractionURIs" : [
      "spotify:track:0pT28a92cnz0G3LbZyGYpf"
    ]
  },
  {
    "platform" : "ANDROID",
    "searchTime" : "2020-02-01T03:18:34.178Z[UTC]",
    "searchQuery" : "swi",
    "searchInteractionURIs" : [
      "spotify:track:3CgZCQyuyxHRMWB9BTwmni"
    ]
  },
  {
    "platform" : "ANDROID",
    "searchTime" : "2020-02-02T03:40:11.559Z[UTC]",
    "searchQuery" : "tiied",
    "searchInteractionURIs" : [
      "spotify:track:4kswfYbJFf6FPzMElZmtve"
    ]
  },
  {
    "platform" : "ANDROID",
    "searchTime" : "2020-02-02T05:44:12.384Z[UTC]",
    "searchQuery" : "shakira",
    "searchInteractionURIs" : [
      "spotify:search:albums:shakira"
    ]
  },
  {
    "platform" : "ANDROID",
    "searchTime" : "2020-02-02T05:44:26.657Z[UTC]",
    "searchQuery" : "shakira",
    "searchInteractionURIs" : [
      "spotify:album:4DyMK9x2gnmRkRa16zHaEV",
      "spotify:album:5u0OuxRnf3FzvZR07xAxL2"
    ]
  },
  {
    "platform" : "ANDROID",
    "searchTime" : "2020-02-02T07:45:19.265Z[UTC]",
    "searchQuery" : "shakira",
    "searchInteractionURIs" : [
    ]
  },
  {
    "platform" : "ANDROID",
    "searchTime" : "2020-02-02T11:15:24.282Z[UTC]",
    "searchQuery" : "s",
    "searchInteractionURIs" : [
    ]
  },
  {
    "platform" : "ANDROID",
    "searchTime" : "2020-02-02T11:16:00.163Z[UTC]",
    "searchQuery" : "sleep",
    "searchInteractionURIs" : [
      "spotify:playlist:37i9dQZF1DWZd79rJ6a7lp"
    ]
  },
  {
    "platform" : "ANDROID",
    "searchTime" : "2020-02-03T03:51:43.017Z[UTC]",
    "searchQuery" : "less i ",
    "searchInteractionURIs" : [
      "spotify:track:6K4t31amVTZDgR3sKmwUJJ"
    ]
  },
  {
    "platform" : "ANDROID",
    "searchTime" : "2020-02-06T07:16:28.315Z[UTC]",
    "searchQuery" : "make it b",
    "searchInteractionURIs" : [
      "spotify:track:4SBVWkRIMJ6WBCYPvr5Bwr"
    ]
  },
  {
    "platform" : "ANDROID",
    "searchTime" : "2020-02-06T09:12:24.782Z[UTC]",
    "searchQuery" : "no",
    "searchInteractionURIs" : [
    ]
  },
  {
    "platform" : "ANDROID",
    "searchTime" : "2020-02-08T22:19:40.157Z[UTC]",
    "searchQuery" : "wildin",
    "searchInteractionURIs" : [
      "spotify:track:4LGg2NY9eHp0jF3L1WbCNl"
    ]
  },
  {
    "platform" : "ANDROID",
    "searchTime" : "2020-02-09T23:08:18.930Z[UTC]",
    "searchQuery" : "dumb ",
    "searchInteractionURIs" : [
      ""
    ]
  },
  {
    "platform" : "ANDROID",
    "searchTime" : "2020-02-09T23:08:19.828Z[UTC]",
    "searchQuery" : "dumb love",
    "searchInteractionURIs" : [
      "spotify:track:42YStFZisN7OLfdEatf8w3",
      ""
    ]
  },
  {
    "platform" : "ANDROID",
    "searchTime" : "2020-02-09T23:08:51.276Z[UTC]",
    "searchQuery" : "f",
    "searchInteractionURIs" : [
      ""
    ]
  },
  {
    "platform" : "ANDROID",
    "searchTime" : "2020-02-09T23:08:53.667Z[UTC]",
    "searchQuery" : "friday nor",
    "searchInteractionURIs" : [
      ""
    ]
  },
  {
    "platform" : "ANDROID",
    "searchTime" : "2020-02-09T23:08:54.598Z[UTC]",
    "searchQuery" : "friday nornint",
    "searchInteractionURIs" : [
      "spotify:track:5gYGXwHud7JFReP9W61wGt"
    ]
  },
  {
    "platform" : "ANDROID",
    "searchTime" : "2020-02-09T23:11:28.925Z[UTC]",
    "searchQuery" : "frida",
    "searchInteractionURIs" : [
      ""
    ]
  },
  {
    "platform" : "ANDROID",
    "searchTime" : "2020-02-09T23:11:32.954Z[UTC]",
    "searchQuery" : "drugs an",
    "searchInteractionURIs" : [
      "spotify:track:4wzscvBb9JkSfiet1A8UQu"
    ]
  },
  {
    "platform" : "ANDROID",
    "searchTime" : "2020-02-09T23:15:00.608Z[UTC]",
    "searchQuery" : "dr",
    "searchInteractionURIs" : [
      ""
    ]
  },
  {
    "platform" : "ANDROID",
    "searchTime" : "2020-02-09T23:15:01.827Z[UTC]",
    "searchQuery" : "droog",
    "searchInteractionURIs" : [
      "spotify:track:4isFUxQUxqEGUbwnYIV1se"
    ]
  },
  {
    "platform" : "ANDROID",
    "searchTime" : "2020-02-09T23:45:39.332Z[UTC]",
    "searchQuery" : "some girl",
    "searchInteractionURIs" : [
      "spotify:track:6wOdpwaVrRtWlVSQNMBNQU"
    ]
  },
  {
    "platform" : "ANDROID",
    "searchTime" : "2020-02-11T04:17:36.530Z[UTC]",
    "searchQuery" : "shakir",
    "searchInteractionURIs" : [
      "spotify:artist:0EmeFodog0BfCgMzAIvKQp"
    ]
  },
  {
    "platform" : "ANDROID",
    "searchTime" : "2020-02-11T04:34:16.791Z[UTC]",
    "searchQuery" : "the",
    "searchInteractionURIs" : [
      ""
    ]
  },
  {
    "platform" : "ANDROID",
    "searchTime" : "2020-02-11T04:34:26.578Z[UTC]",
    "searchQuery" : "wh",
    "searchInteractionURIs" : [
      ""
    ]
  },
  {
    "platform" : "ANDROID",
    "searchTime" : "2020-02-11T04:34:44.109Z[UTC]",
    "searchQuery" : "when we we",
    "searchInteractionURIs" : [
      ""
    ]
  },
  {
    "platform" : "ANDROID",
    "searchTime" : "2020-02-11T04:34:55.545Z[UTC]",
    "searchQuery" : "young",
    "searchInteractionURIs" : [
      ""
    ]
  },
  {
    "platform" : "ANDROID",
    "searchTime" : "2020-02-11T04:35:07.591Z[UTC]",
    "searchQuery" : "maps",
    "searchInteractionURIs" : [
      "spotify:track:0hDQV9X1Da5JrwhK8gu86p",
      "spotify:track:0hDQV9X1Da5JrwhK8gu86p",
      ""
    ]
  },
  {
    "platform" : "ANDROID",
    "searchTime" : "2020-02-11T04:43:49.363Z[UTC]",
    "searchQuery" : "cage the",
    "searchInteractionURIs" : [
      "spotify:artist:26T3LtbuGT1Fu9m0eRq5X3"
    ]
  },
  {
    "platform" : "ANDROID",
    "searchTime" : "2020-02-11T05:17:18.019Z[UTC]",
    "searchQuery" : "kaala",
    "searchInteractionURIs" : [
      "spotify:track:780zqvhD7SvK0sMGheplPf"
    ]
  },
  {
    "platform" : "ANDROID",
    "searchTime" : "2020-02-14T10:09:52.881Z[UTC]",
    "searchQuery" : "hindu",
    "searchInteractionURIs" : [
      "spotify:artist:2IQZLHkFO0Dk4nqd3jDMAj"
    ]
  },
  {
    "platform" : "ANDROID",
    "searchTime" : "2020-02-14T10:39:06.269Z[UTC]",
    "searchQuery" : "blo",
    "searchInteractionURIs" : [
      "spotify:album:3mH6qwIy9crq0I9YQbOuDf"
    ]
  },
  {
    "platform" : "DESKTOP",
    "searchTime" : "2020-02-14T23:03:31.260Z[UTC]",
    "searchQuery" : "damn it ",
    "searchInteractionURIs" : [
      "spotify:track:0HOqINudNgQFpg1le5Hnqe"
    ]
  },
  {
    "platform" : "DESKTOP",
    "searchTime" : "2020-02-14T23:11:24.843Z[UTC]",
    "searchQuery" : "wildin",
    "searchInteractionURIs" : [
      "spotify:track:4LGg2NY9eHp0jF3L1WbCNl"
    ]
  },
  {
    "platform" : "ANDROID",
    "searchTime" : "2020-02-15T03:54:16.997Z[UTC]",
    "searchQuery" : "tame",
    "searchInteractionURIs" : [
      "spotify:artist:5INjqkS1o8h1imAzPqGZBb"
    ]
  },
  {
    "platform" : "ANDROID",
    "searchTime" : "2020-02-15T08:48:49.245Z[UTC]",
    "searchQuery" : " i",
    "searchInteractionURIs" : [
      ""
    ]
  },
  {
    "platform" : "ANDROID",
    "searchTime" : "2020-02-15T08:48:50.498Z[UTC]",
    "searchQuery" : "c",
    "searchInteractionURIs" : [
      "spotify:album:5sY6UIQ32GqwMLAfSNEaXb"
    ]
  },
  {
    "platform" : "ANDROID",
    "searchTime" : "2020-02-15T19:18:55.853Z[UTC]",
    "searchQuery" : "them ch",
    "searchInteractionURIs" : [
      "spotify:track:1dcaQEzJ1sU9ImjDHLV5mh"
    ]
  },
  {
    "platform" : "ANDROID",
    "searchTime" : "2020-02-15T19:28:26.749Z[UTC]",
    "searchQuery" : "t",
    "searchInteractionURIs" : [
      ""
    ]
  },
  {
    "platform" : "ANDROID",
    "searchTime" : "2020-02-15T19:28:46.759Z[UTC]",
    "searchQuery" : "veni",
    "searchInteractionURIs" : [
      "spotify:album:2DOiha5oI19Dmw5M9ryHD8"
    ]
  },
  {
    "platform" : "ANDROID",
    "searchTime" : "2020-02-15T19:32:39.014Z[UTC]",
    "searchQuery" : "droog",
    "searchInteractionURIs" : [
      "spotify:track:4isFUxQUxqEGUbwnYIV1se",
      ""
    ]
  },
  {
    "platform" : "ANDROID",
    "searchTime" : "2020-02-15T20:58:34.709Z[UTC]",
    "searchQuery" : "iso",
    "searchInteractionURIs" : [
      ""
    ]
  },
  {
    "platform" : "ANDROID",
    "searchTime" : "2020-02-15T20:58:36.853Z[UTC]",
    "searchQuery" : "know wgar",
    "searchInteractionURIs" : [
      "spotify:track:00hh0NPClA0PJetfwn4k5R"
    ]
  },
  {
    "platform" : "ANDROID",
    "searchTime" : "2020-02-15T21:01:33.351Z[UTC]",
    "searchQuery" : "kno",
    "searchInteractionURIs" : [
      ""
    ]
  },
  {
    "platform" : "ANDROID",
    "searchTime" : "2020-02-15T21:01:35.672Z[UTC]",
    "searchQuery" : "isolation",
    "searchInteractionURIs" : [
      "spotify:album:4EPQtdq6vvwxuYeQTrwDVY"
    ]
  },
  {
    "platform" : "ANDROID",
    "searchTime" : "2020-02-17T04:16:44.051Z[UTC]",
    "searchQuery" : "blind",
    "searchInteractionURIs" : [
      "spotify:track:0sf12qNH5qcw8qpgymFOqD"
    ]
  },
  {
    "platform" : "ANDROID",
    "searchTime" : "2020-02-17T19:41:03.028Z[UTC]",
    "searchQuery" : "tame",
    "searchInteractionURIs" : [
      "spotify:artist:5INjqkS1o8h1imAzPqGZBb"
    ]
  },
  {
    "platform" : "ANDROID",
    "searchTime" : "2020-02-18T03:41:26.798Z[UTC]",
    "searchQuery" : "dissect",
    "searchInteractionURIs" : [
      "spotify:show:2b025hq3gJ17tQdxS3aV43"
    ]
  },
  {
    "platform" : "ANDROID",
    "searchTime" : "2020-02-18T04:18:15.512Z[UTC]",
    "searchQuery" : "nostalgia ultra",
    "searchInteractionURIs" : [
      "spotify:search:albums:nostalgia%20ultra",
      "spotify:playlist:7uVNmWTQmGQFPT1dXEAbEq"
    ]
  }
]